setup.py
distributions/Binomialdistribution.py
distributions/Gaussiandistribution.py
distributions/Generaldistribution.py
distributions/__init__.py
lyh_distributions.egg-info/PKG-INFO
lyh_distributions.egg-info/SOURCES.txt
lyh_distributions.egg-info/dependency_links.txt
lyh_distributions.egg-info/not-zip-safe
lyh_distributions.egg-info/top_level.txt